<?xml version="1.0" encoding="utf-8" ?>
<ha:AggregateTestResultSet
  xmlns:xs="http://www.w3.org/2001/XMLSchema"
  xmlns:xsi="http://www.w3.org/2001/XMLSchema-instance"
  xmlns:ua="http://opcfoundation.org/UA/2008/02/Types.xsd"
  xmlns:ha="http://osisoft.com/UA/Server/PIUAServer/HATestConfiguration.xsd"
  >
  <!--Delta data with good bouding value-->
    <ha:AggregateTestResult>
      <ha:DataValues>
        <ha:DataValueEntry>
          <ha:SourceTimestamp>2009-08-13T10:00:10-05:00</ha:SourceTimestamp>
          <ha:StatusCode>Calculated,Good</ha:StatusCode>
          <ha:Value>0</ha:Value>
        </ha:DataValueEntry>
        <ha:DataValueEntry>
          <ha:SourceTimestamp>2009-08-13T10:00:15-05:00</ha:SourceTimestamp>
          <ha:StatusCode>Calculated,BadNoData</ha:StatusCode>
        </ha:DataValueEntry>
      </ha:DataValues>
      <ha:Details>
        <ua:StartTime>2009-08-13T10:00:10-05:00</ua:StartTime>
        <ua:EndTime>2009-08-13T10:00:20-05:00</ua:EndTime>
        <ua:ResampleInterval>5000</ua:ResampleInterval>
      </ha:Details>
      <ha:TestDataName>TestData1</ha:TestDataName>
    </ha:AggregateTestResult>

    <!-- Delta data with bad bounding value-->
    <ha:AggregateTestResult>
      <ha:DataValues>
        <ha:DataValueEntry>
          <ha:SourceTimestamp>2009-08-13T10:00:10-05:00</ha:SourceTimestamp>
          <ha:StatusCode>Calculated,BadNoData</ha:StatusCode>
        </ha:DataValueEntry>
        <ha:DataValueEntry>
          <ha:SourceTimestamp>2009-08-13T10:00:15-05:00</ha:SourceTimestamp>
          <ha:StatusCode>Calculated,BadNoData</ha:StatusCode>
        </ha:DataValueEntry>
      </ha:DataValues>
      <ha:Details>
        <ua:StartTime>2009-08-13T10:00:10-05:00</ua:StartTime>
        <ua:EndTime>2009-08-13T10:00:20-05:00</ua:EndTime>
        <ua:ResampleInterval>5000</ua:ResampleInterval>
      </ha:Details>
      <ha:TestDataName>TestData2</ha:TestDataName>
    </ha:AggregateTestResult>

    <!-- Delta data with no good end bounding value-->
    <ha:AggregateTestResult>
      <ha:DataValues>
        <ha:DataValueEntry>
          <ha:SourceTimestamp>2009-08-13T10:00:35-05:00</ha:SourceTimestamp>
          <ha:StatusCode>Calculated,BadNoData</ha:StatusCode>
        </ha:DataValueEntry>
        <ha:DataValueEntry>
          <ha:SourceTimestamp>2009-08-13T10:00:40-05:00</ha:SourceTimestamp>
          <ha:StatusCode>Calculated,UncertainDataSubnormal</ha:StatusCode>
          <!--<ha:Value>0</ha:Value>, need clarification to know whether the returned value is zero or null-->
        </ha:DataValueEntry>
        <ha:DataValueEntry>
          <ha:SourceTimestamp>2009-08-13T10:00:45-05:00</ha:SourceTimestamp>
          <ha:StatusCode>Calculated,BadNoData</ha:StatusCode>
        </ha:DataValueEntry>
        <ha:DataValueEntry>
          <ha:SourceTimestamp>2009-08-13T10:00:50-05:00</ha:SourceTimestamp>
          <ha:StatusCode>Calculated,Good</ha:StatusCode>
          <ha:Value>0</ha:Value>
        </ha:DataValueEntry>
        <ha:DataValueEntry>
          <ha:SourceTimestamp>2009-08-13T10:00:55-05:00</ha:SourceTimestamp>
          <ha:StatusCode>Calculated,BadNoData</ha:StatusCode>
        </ha:DataValueEntry>
      </ha:DataValues>
      <ha:Details>
        <ua:StartTime>2009-08-13T10:00:35-05:00</ua:StartTime>
        <ua:EndTime>2009-08-13T10:01:00-05:00</ua:EndTime>
        <ua:ResampleInterval>5000</ua:ResampleInterval>
      </ha:Details>
      <ha:TestDataName>TestData1</ha:TestDataName>
    </ha:AggregateTestResult>
    <ha:AggregateTestResult>
      <ha:DataValues>
        <ha:DataValueEntry>
          <ha:SourceTimestamp>2009-08-13T10:00:35-05:00</ha:SourceTimestamp>
          <ha:StatusCode>Calculated,Good</ha:StatusCode>
          <ha:Value>0</ha:Value>
        </ha:DataValueEntry>
        <ha:DataValueEntry>
          <ha:SourceTimestamp>2009-08-13T10:00:40-05:00</ha:SourceTimestamp>
          <ha:StatusCode>Calculated,UncertainDataSubnormal</ha:StatusCode>
          <!--<ha:Value>0</ha:Value>, need clarification to know whether the returned value is zero or null-->
        </ha:DataValueEntry>
        <ha:DataValueEntry>
          <ha:SourceTimestamp>2009-08-13T10:00:45-05:00</ha:SourceTimestamp>
          <ha:StatusCode>Calculated,Good</ha:StatusCode>
          <ha:Value>0</ha:Value>
        </ha:DataValueEntry>
        <ha:DataValueEntry>
          <ha:SourceTimestamp>2009-08-13T10:00:50-05:00</ha:SourceTimestamp>
          <ha:StatusCode>Calculated,Good</ha:StatusCode>
          <ha:Value>0</ha:Value>
        </ha:DataValueEntry>
        <ha:DataValueEntry>
          <ha:SourceTimestamp>2009-08-13T10:00:55-05:00</ha:SourceTimestamp>
          <ha:StatusCode>Calculated,BadNoData</ha:StatusCode>
        </ha:DataValueEntry>
      </ha:DataValues>
      <ha:Details>
        <ua:StartTime>2009-08-13T10:00:35-05:00</ua:StartTime>
        <ua:EndTime>2009-08-13T10:01:00-05:00</ua:EndTime>
        <ua:ResampleInterval>5000</ua:ResampleInterval>
      </ha:Details>
      <ha:TestDataName>TestData2</ha:TestDataName>
    </ha:AggregateTestResult>

    <!-- Delta data with partial intervals.-->
    <ha:AggregateTestResult>
      <ha:DataValues>
        <ha:DataValueEntry>
          <ha:SourceTimestamp>2009-08-13T10:00:05-05:00</ha:SourceTimestamp>
          <ha:StatusCode>Calculated,Good</ha:StatusCode>
          <ha:Value>10</ha:Value>
        </ha:DataValueEntry>
        <ha:DataValueEntry>
          <ha:SourceTimestamp>2009-08-13T10:00:21-05:00</ha:SourceTimestamp>
          <ha:StatusCode>Partial,Calculated,Good</ha:StatusCode>
          <ha:Value>0</ha:Value>
        </ha:DataValueEntry>
      </ha:DataValues>
      <ha:Details>
        <ua:StartTime>2009-08-13T10:00:05-05:00</ua:StartTime>
        <ua:EndTime>2009-08-13T10:00:35-05:00</ua:EndTime>
        <ua:ResampleInterval>16000</ua:ResampleInterval>
      </ha:Details>
      <ha:TestDataName>TestData1</ha:TestDataName>
    </ha:AggregateTestResult>
    <ha:AggregateTestResult>
      <ha:DataValues>
        <ha:DataValueEntry>
          <ha:SourceTimestamp>2009-08-13T10:00:05-05:00</ha:SourceTimestamp>
          <ha:StatusCode>Calculated,BadNoData</ha:StatusCode>
        </ha:DataValueEntry>
        <ha:DataValueEntry>
          <ha:SourceTimestamp>2009-08-13T10:00:21-05:00</ha:SourceTimestamp>
          <ha:StatusCode>Partial,Calculated,Good</ha:StatusCode>
          <ha:Value>5</ha:Value>
        </ha:DataValueEntry>
      </ha:DataValues>
      <ha:Details>
        <ua:StartTime>2009-08-13T10:00:05-05:00</ua:StartTime>
        <ua:EndTime>2009-08-13T10:00:35-05:00</ua:EndTime>
        <ua:ResampleInterval>16000</ua:ResampleInterval>
      </ha:Details>
      <ha:TestDataName>TestData2</ha:TestDataName>
    </ha:AggregateTestResult>
</ha:AggregateTestResultSet>


